Py_Keyboard/API.py
Py_Keyboard/HID.py
Py_Keyboard/HID_old.py
Py_Keyboard/__init__.py
Py_Keyboard/ada_hid.py
Py_Keyboard/byte_decoder.py
Py_Keyboard/keycode.py
Py_Keyboard-0.0.2.dist-info/METADATA
Py_Keyboard-0.0.2.dist-info/WHEEL
Py_Keyboard-0.0.2.dist-info/top_level.txt
Py_Keyboard-0.0.2.dist-info/RECORD
