Metadata-Version: 2.1
Name: Py-Keyboard
Version: 0.0.2
Summary: Python wrapper for hid device
Home-page: https://github.com/Danny-Dasilva/Py_Keyboard
Author: Danny Dasilva
Author-email: dannydasilva.solutions@gmail.com
License: UNKNOWN
Platform: UNKNOWN
Classifier: Programming Language :: Python :: 3
